{
  "version": "3.3.10",
  "flags": {},
  "shapes": [
    {
      "kie_linking": [],
      "label": "car",
      "score": 0.7263023853302002,
      "points": [
        [
          533.1642456054688,
          391.24346923828125
        ],
        [
          722.0966796875,
          391.24346923828125
        ],
        [
          722.0966796875,
          457.19873046875
        ],
        [
          533.1642456054688,
          457.19873046875
        ]
      ],
      "group_id": null,
      "description": null,
      "difficult": false,
      "shape_type": "rectangle",
      "flags": {},
      "attributes": {}
    },
    {
      "kie_linking": [],
      "label": "car",
      "score": 0.7065389752388,
      "points": [
        [
          1032.11865234375,
          294.05267333984375
        ],
        [
          1279.5699462890625,
          294.05267333984375
        ],
        [
          1279.5699462890625,
          670.79541015625
        ],
        [
          1032.11865234375,
          670.79541015625
        ]
      ],
      "group_id": null,
      "description": null,
      "difficult": false,
      "shape_type": "rectangle",
      "flags": {},
      "attributes": {}
    },
    {
      "kie_linking": [],
      "label": "car",
      "score": 0.2684508264064789,
      "points": [
        [
          688.7363891601562,
          379.541748046875
        ],
        [
          800.48583984375,
          379.541748046875
        ],
        [
          800.48583984375,
          436.901611328125
        ],
        [
          688.7363891601562,
          436.901611328125
        ]
      ],
      "group_id": null,
      "description": null,
      "difficult": false,
      "shape_type": "rectangle",
      "flags": {},
      "attributes": {}
    }
  ],
  "imagePath": "sand_storm-021.jpg",
  "imageData": null,
  "imageHeight": 798,
  "imageWidth": 1280,
  "description": ""
}