{
  "version": "3.3.10",
  "flags": {},
  "shapes": [
    {
      "kie_linking": [],
      "label": "car",
      "score": 0.932715892791748,
      "points": [
        [
          527.277587890625,
          510.54595947265625
        ],
        [
          747.7169799804688,
          510.54595947265625
        ],
        [
          747.7169799804688,
          684.6117553710938
        ],
        [
          527.277587890625,
          684.6117553710938
        ]
      ],
      "group_id": null,
      "description": null,
      "difficult": false,
      "shape_type": "rectangle",
      "flags": {},
      "attributes": {}
    },
    {
      "kie_linking": [],
      "label": "car",
      "score": 0.9044722318649292,
      "points": [
        [
          1457.92529296875,
          633.194091796875
        ],
        [
          1599.12255859375,
          633.194091796875
        ],
        [
          1599.12255859375,
          894.114990234375
        ],
        [
          1457.92529296875,
          894.114990234375
        ]
      ],
      "group_id": null,
      "description": null,
      "difficult": false,
      "shape_type": "rectangle",
      "flags": {},
      "attributes": {}
    },
    {
      "kie_linking": [],
      "label": "car",
      "score": 0.8462233543395996,
      "points": [
        [
          1200.882568359375,
          516.6414794921875
        ],
        [
          1463.8623046875,
          516.6414794921875
        ],
        [
          1463.8623046875,
          692.1697998046875
        ],
        [
          1200.882568359375,
          692.1697998046875
        ]
      ],
      "group_id": null,
      "description": null,
      "difficult": false,
      "shape_type": "rectangle",
      "flags": {},
      "attributes": {}
    },
    {
      "kie_linking": [],
      "label": "car",
      "score": 0.8011481761932373,
      "points": [
        [
          784.8624877929688,
          515.369873046875
        ],
        [
          881.6483154296875,
          515.369873046875
        ],
        [
          881.6483154296875,
          602.527587890625
        ],
        [
          784.8624877929688,
          602.527587890625
        ]
      ],
      "group_id": null,
      "description": null,
      "difficult": false,
      "shape_type": "rectangle",
      "flags": {},
      "attributes": {}
    },
    {
      "kie_linking": [],
      "label": "car",
      "score": 0.7962433099746704,
      "points": [
        [
          907.4542236328125,
          524.4940185546875
        ],
        [
          994.8143920898438,
          524.4940185546875
        ],
        [
          994.8143920898438,
          600.5009155273438
        ],
        [
          907.4542236328125,
          600.5009155273438
        ]
      ],
      "group_id": null,
      "description": null,
      "difficult": false,
      "shape_type": "rectangle",
      "flags": {},
      "attributes": {}
    },
    {
      "kie_linking": [],
      "label": "car",
      "score": 0.5756471753120422,
      "points": [
        [
          996.9813232421875,
          530.58984375
        ],
        [
          1125.8018798828125,
          530.58984375
        ],
        [
          1125.8018798828125,
          627.405029296875
        ],
        [
          996.9813232421875,
          627.405029296875
        ]
      ],
      "group_id": null,
      "description": null,
      "difficult": false,
      "shape_type": "rectangle",
      "flags": {},
      "attributes": {}
    },
    {
      "kie_linking": [],
      "label": "car",
      "score": 0.5233014225959778,
      "points": [
        [
          0.23582935333251953,
          495.3028869628906
        ],
        [
          94.91226196289062,
          495.3028869628906
        ],
        [
          94.91226196289062,
          573.638671875
        ],
        [
          0.23582935333251953,
          573.638671875
        ]
      ],
      "group_id": null,
      "description": null,
      "difficult": false,
      "shape_type": "rectangle",
      "flags": {},
      "attributes": {}
    },
    {
      "kie_linking": [],
      "label": "car",
      "score": 0.4621366560459137,
      "points": [
        [
          134.59323120117188,
          504.2729187011719
        ],
        [
          224.02606201171875,
          504.2729187011719
        ],
        [
          224.02606201171875,
          564.9984130859375
        ],
        [
          134.59323120117188,
          564.9984130859375
        ]
      ],
      "group_id": null,
      "description": null,
      "difficult": false,
      "shape_type": "rectangle",
      "flags": {},
      "attributes": {}
    }
  ],
  "imagePath": "sand_storm-039.jpg",
  "imageData": null,
  "imageHeight": 900,
  "imageWidth": 1600,
  "description": ""
}